{
  "scan_info": {
    "timestamp": "2026-02-07T13:17:20.037584",
    "results_file": "detection_results_20260207_131718.csv",
    "total_records": 90105
  },
  "summary": {
    "total_analyzed": 90105,
    "threats_detected": 20159,
    "benign_traffic": 69946,
    "threat_percentage": 22.37,
    "benign_percentage": 77.63
  },
  "probability_statistics": {
    "mean": 0.22570222714699886,
    "median": 8.867621303920714e-09,
    "std": 0.4091063776598784,
    "min": 2.9126263033363298e-12,
    "max": 1.0
  },
  "top_threats": [
    {
      "index": 13,
      "probability": 1.0,
      "Destination Port": "80",
      "Total Fwd Packets": "18",
      "Flow Bytes/s": "47.83464764",
      "Flow Packets/s": "0.175432693"
    },
    {
      "index": 16,
      "probability": 1.0,
      "Destination Port": "63281",
      "Total Fwd Packets": "3",
      "Flow Bytes/s": "7400000.0",
      "Flow Packets/s": "600000.0"
    },
    {
      "index": 18,
      "probability": 1.0,
      "Destination Port": "80",
      "Total Fwd Packets": "3",
      "Flow Bytes/s": "26027.11223",
      "Flow Packets/s": "15.66146184"
    },
    {
      "index": 23,
      "probability": 1.0,
      "Destination Port": "80",
      "Total Fwd Packets": "6",
      "Flow Bytes/s": "139.2866727",
      "Flow Packets/s": "0.151944847"
    },
    {
      "index": 29,
      "probability": 1.0,
      "Destination Port": "80",
      "Total Fwd Packets": "3",
      "Flow Bytes/s": "310395.432",
      "Flow Packets/s": "213.4585624"
    },
    {
      "index": 38,
      "probability": 1.0,
      "Destination Port": "80",
      "Total Fwd Packets": "8",
      "Flow Bytes/s": "118.8865475",
      "Flow Packets/s": "0.12232175"
    },
    {
      "index": 44,
      "probability": 1.0,
      "Destination Port": "80",
      "Total Fwd Packets": "3",
      "Flow Bytes/s": "26053.03373",
      "Flow Packets/s": "15.68514975"
    },
    {
      "index": 50,
      "probability": 1.0,
      "Destination Port": "80",
      "Total Fwd Packets": "3",
      "Flow Bytes/s": "7211.696426",
      "Flow Packets/s": "4.959474891"
    },
    {
      "index": 62,
      "probability": 1.0,
      "Destination Port": "80",
      "Total Fwd Packets": "3",
      "Flow Bytes/s": "16822.6056",
      "Flow Packets/s": "11.56888548"
    },
    {
      "index": 64,
      "probability": 1.0,
      "Destination Port": "80",
      "Total Fwd Packets": "5",
      "Flow Bytes/s": "121.7841964",
      "Flow Packets/s": "0.132131076"
    }
  ],
  "port_analysis": {
    "80": 13619,
    "443": 2882,
    "53": 156,
    "389": 39,
    "0": 36,
    "3268": 36,
    "445": 36,
    "5353": 24,
    "49666": 12,
    "55074": 12
  }
}